README.rst
setup.cfg
setup.py
nagare/__init__.py
nagare/contrib/__init__.py
nagare/contrib/jquery/__init__.py
nagare/contrib/jquery/wsgi.py
nagare/contrib/jquery/namespaces/__init__.py
nagare/contrib/jquery/namespaces/xhtml5.py
nagare_jquery.egg-info/PKG-INFO
nagare_jquery.egg-info/SOURCES.txt
nagare_jquery.egg-info/dependency_links.txt
nagare_jquery.egg-info/namespace_packages.txt
nagare_jquery.egg-info/not-zip-safe
nagare_jquery.egg-info/requires.txt
nagare_jquery.egg-info/top_level.txt