Metadata-Version: 1.0
Name: nagare-jquery
Version: 0.0.2a1
Summary: Nagare renderer that uses jquery as async backend
Home-page: https://github.com/Alzakath/nagare-jquery
Author: UNKNOWN
Author-email: herve.coatanhay@gmail.com
License: UNKNOWN
Platform: UNKNOWN
